osn_currencies_tools/__init__.py
osn_currencies_tools/currency_live.py
osn_currencies_tools/data.py
osn_currencies_tools/errors.py
osn_currencies_tools/exchange_rate.py
osn_currencies_tools/open_exchange_rates.py
osn_currencies_tools-1.0.0.dist-info/METADATA
osn_currencies_tools-1.0.0.dist-info/WHEEL
osn_currencies_tools-1.0.0.dist-info/top_level.txt
osn_currencies_tools-1.0.0.dist-info/RECORD
