Metadata-Version: 2.2
Name: osn-currencies-tools
Version: 1.0.0
Summary: osn-currencies-tools is a Python library for easy currency conversion and information retrieval, providing real-time exchange rates and a comprehensive list of currency symbols and tags.
Author: oddshellnick
Author-email: oddshellnick.programming@gmail.com
Requires-Dist: setuptools>=75.1.0
Requires-Dist: osn-requests>=1.0.0
Dynamic: author
Dynamic: author-email
Dynamic: description
Dynamic: description-content-type
Dynamic: requires-dist
Dynamic: summary
